{
  "search": ["upper_25","upper_50","upper_75","upper_90","upper_95"],
  "query": {
    "columns":[
      {"text":"Time","type":"time"},
      {"text":"Country","type":"string"},
      {"text":"Number","type":"number"}
    ],
    "rows":[
      [1234567,"SE",123],
      [1234567,"DE",231],
      [1234567,"US",321]
    ],
    "type":"table"
  },
  "annotations": [
    {
      "text": "text shown in body",
      "title": "Annotation Title",
      "isRegion": true,
      "time": "timestamp",
      "timeEnd": "timestamp",
      "tags": ["tag1"]
    }
  ]
}